src/__init__.py
src/main.py
dns_check-2.0.0.dist-info/LICENSE
dns_check-2.0.0.dist-info/METADATA
dns_check-2.0.0.dist-info/WHEEL
dns_check-2.0.0.dist-info/entry_points.txt
dns_check-2.0.0.dist-info/top_level.txt
dns_check-2.0.0.dist-info/RECORD
