Metadata-Version: 2.1
Name: dns-check
Version: 2.0.0
Summary: Performing DNS tests
Home-page: https://github.com/hesami/dns-check
Author: hesami
Classifier: Programming Language :: Python :: 3
Classifier: License :: OSI Approved :: MIT License
Classifier: Operating System :: OS Independent
Requires-Python: >=3.6
License-File: LICENSE
Requires-Dist: requests
Requires-Dist: geopy
Requires-Dist: tqdm
Requires-Dist: colorama
Requires-Dist: tabulate
